infinity_arcade/__init__.py
infinity_arcade/arcade_games.py
infinity_arcade/cli.py
infinity_arcade/game_launcher.py
infinity_arcade/game_orchestrator.py
infinity_arcade/llm_service.py
infinity_arcade/main.py
infinity_arcade/utils.py
infinity_arcade/version.py
infinity_arcade/builtin_games/__init__.py
infinity_arcade/builtin_games/rainbow_space_invaders.py
infinity_arcade/builtin_games/snake_moving_food.py
infinity_arcade/static/app.js
infinity_arcade/static/favicon.ico
infinity_arcade/static/style.css
infinity_arcade/templates/index.html
infinity_arcade-0.2.2.dist-info/licenses/LICENSE
lemonade_client/__init__.py
lemonade_client/lemonade_client.py
infinity_arcade-0.2.2.dist-info/METADATA
infinity_arcade-0.2.2.dist-info/WHEEL
infinity_arcade-0.2.2.dist-info/entry_points.txt
infinity_arcade-0.2.2.dist-info/top_level.txt
infinity_arcade-0.2.2.dist-info/RECORD
